setup.cfg
setup.py
ptoken/__init__.py
ptoken/cipher.py
ptoken/payload.py
ptoken/signer.py
ptoken/token_manager.py
ptoken.egg-info/PKG-INFO
ptoken.egg-info/SOURCES.txt
ptoken.egg-info/dependency_links.txt
ptoken.egg-info/requires.txt
ptoken.egg-info/top_level.txt
ptoken/cache/__init__.py
ptoken/cache/backend.py
ptoken/cache/frontend.py