Metadata-Version: 1.1
Name: ptoken
Version: 0.1
Summary: Token Helper
Home-page: https://github.com/tuanlq11/python_token
Author: Fallen
Author-email: tuanlq.it@gmail.com
License: UNKNOWN
Download-URL: https://github.com/tuanlq11/python_token/tarball/0.1
Keywords: security
Platform: UNKNOWN
